geofabric/__init__.py
geofabric/__main__.py
geofabric/_version.py
geofabric/cache.py
geofabric/config.py
geofabric/dataset.py
geofabric/errors.py
geofabric/protocols.py
geofabric/py.typed
geofabric/query.py
geofabric/registry.py
geofabric/roi.py
geofabric/spatial.py
geofabric/sql_utils.py
geofabric/util.py
geofabric/validation.py
geofabric/cli/__init__.py
geofabric/cli/app.py
geofabric/engines/__init__.py
geofabric/engines/duckdb_engine.py
geofabric/sinks/__init__.py
geofabric/sinks/pmtiles.py
geofabric/sources/__init__.py
geofabric/sources/cloud.py
geofabric/sources/files.py
geofabric/sources/overture.py
geofabric/sources/postgis.py
geofabric/sources/stac.py
geofabric-1.0.0.dist-info/METADATA
geofabric-1.0.0.dist-info/WHEEL
geofabric-1.0.0.dist-info/entry_points.txt
geofabric-1.0.0.dist-info/licenses/LICENSE
geofabric-1.0.0.dist-info/RECORD
