Metadata-Version: 2.4
Name: geofabric
Version: 1.0.0
Summary: Query geospatial sources, analyze at scale, and publish results with a consistent API.
Author: Marcos Tulio Fermin Lopez
License: MIT
License-File: LICENSE
Keywords: duckdb,geoarrow,geopandas,geoparquet,geospatial,gis,pmtiles,stac
Classifier: Development Status :: 5 - Production/Stable
Classifier: Intended Audience :: Developers
Classifier: Intended Audience :: Science/Research
Classifier: License :: OSI Approved :: MIT License
Classifier: Programming Language :: Python :: 3
Classifier: Programming Language :: Python :: 3.10
Classifier: Programming Language :: Python :: 3.11
Classifier: Programming Language :: Python :: 3.12
Classifier: Typing :: Typed
Requires-Python: >=3.12
Requires-Dist: duckdb>=1.0.0
Requires-Dist: pandas>=2.0.0
Requires-Dist: pyarrow>=14.0.0
Requires-Dist: rich>=13.0.0
Requires-Dist: shapely>=2.0.0
Requires-Dist: typer>=0.12.0
Provides-Extra: all
Requires-Dist: geopandas>=0.14.0; extra == 'all'
Requires-Dist: lonboard>=0.10.0; extra == 'all'
Requires-Dist: pystac-client>=0.7.0; extra == 'all'
Requires-Dist: pystac>=1.10.0; extra == 'all'
Provides-Extra: dev
Requires-Dist: build>=1.2.0; extra == 'dev'
Requires-Dist: mkdocs-material>=9.5.0; extra == 'dev'
Requires-Dist: mkdocs>=1.6.0; extra == 'dev'
Requires-Dist: pdoc>=14.0.0; extra == 'dev'
Requires-Dist: pre-commit>=3.7.0; extra == 'dev'
Requires-Dist: twine>=5.1.0; extra == 'dev'
Provides-Extra: stac
Requires-Dist: pystac-client>=0.7.0; extra == 'stac'
Requires-Dist: pystac>=1.10.0; extra == 'stac'
Provides-Extra: tiles
Requires-Dist: geopandas>=0.14.0; extra == 'tiles'
Provides-Extra: viz
Requires-Dist: geopandas>=0.14.0; extra == 'viz'
Requires-Dist: lonboard>=0.10.0; extra == 'viz'
